{"version":1,"resource":"vscode-userdata:/User/settings.json","entries":[{"id":"x4VN.json","timestamp":1743022279226},{"id":"ElqT.json","timestamp":1743022279236},{"id":"Zu2O.json","timestamp":1743022279529},{"id":"98TH.json","timestamp":1743022279536},{"id":"zLSH.json","timestamp":1743022279543},{"id":"PbVt.json","timestamp":1743022279549},{"id":"TI1L.json","timestamp":1743022279552},{"id":"ouLc.json","timestamp":1743022279556},{"id":"MsFi.json","timestamp":1743022291048},{"id":"eDYd.json","timestamp":1743069990023}]}